ips_api/__init__.py
ips_api/client.py
ips_api/const.py
ips_api/exceptions.py
ips_api/models.py
ips_api/parser.py
ips_api_client-0.1.0.dist-info/licenses/LICENSE
ips_api_client-0.1.0.dist-info/METADATA
ips_api_client-0.1.0.dist-info/WHEEL
ips_api_client-0.1.0.dist-info/top_level.txt
ips_api_client-0.1.0.dist-info/RECORD
