Metadata-Version: 2.4
Name: ips-api-client
Version: 0.1.0
Summary: Async Python client for IPS Controllers pool monitoring system
Home-page: https://github.com/stgarrity/ips-api-client
Author: Steve Garrity
Author-email: Steve Garrity <sgarrity@gmail.com>
License: MIT
Project-URL: Homepage, https://github.com/stgarrity/ips-api-client
Project-URL: Documentation, https://github.com/stgarrity/ips-api-client#readme
Project-URL: Repository, https://github.com/stgarrity/ips-api-client
Project-URL: Issues, https://github.com/stgarrity/ips-api-client/issues
Keywords: ips,pool,chemistry,monitoring,home-assistant
Classifier: Development Status :: 3 - Alpha
Classifier: Intended Audience :: Developers
Classifier: License :: OSI Approved :: MIT License
Classifier: Operating System :: OS Independent
Classifier: Programming Language :: Python :: 3
Classifier: Programming Language :: Python :: 3.9
Classifier: Programming Language :: Python :: 3.10
Classifier: Programming Language :: Python :: 3.11
Classifier: Programming Language :: Python :: 3.12
Classifier: Topic :: Home Automation
Classifier: Topic :: Software Development :: Libraries :: Python Modules
Requires-Python: >=3.9
License-File: LICENSE
Requires-Dist: aiohttp>=3.8.0
Requires-Dist: beautifulsoup4>=4.11.0
Dynamic: author
Dynamic: home-page
Dynamic: license-file
Dynamic: requires-python
